{
  "provider_email": "carla1@gmail.com",
  "dependents": [
    {
      "dependent_illness": "Illness",
      "dependent_name": "komu",
      "dependent_address": "Address",
      "dependent_profile_url": "http://cdn.shephertz.com/repository/files/458f7884154a3afc67bd5c5f24df3d1e6c0852e01e4e272ea3ed79a8d8ac6439/6ab454893564502587769da6bd9d927c38054a13/komu.jpeg",
      "customer_email": "balamscint@gmail.com",
      "dependent_email": "komagan09@gmail.com",
      "dependent_notes": "Note",
      "dependent_age": 65,
      "dependent_contact_no": "8998907769"
    },
    {
      "dependent_illness": "Illness",
      "dependent_name": "Kovendan V",
      "dependent_address": "Address",
      "dependent_profile_url": "http://cdn.shephertz.com/repository/files/458f7884154a3afc67bd5c5f24df3d1e6c0852e01e4e272ea3ed79a8d8ac6439/4bf7564e8907f46ba145b5547ae0639cdc72b9c8/Kovendan_V.jpeg",
      "customer_email": "balamscint@gmail.com",
      "dependent_email": "emailkove@gmail.com",
      "dependent_notes": "Notes",
      "dependent_age": 65,
      "dependent_contact_no": "09619449616"
    }
  ],
  "provider_contact_no": "8956231852",
  "feedbacks": [
    {
      "feedback_message": "Lorem Ipsum is simply dummy text of the printing and typesetting industry. Lorem Ipsum has been the industry's standard dummy text ever since the 1500s.",
      "feedback_raring": 3,
      "feedback_by": "komu",
      "report": 1,
      "feedback_time": "19-01-2016 18:00:00",
      "feedback_by_url": "komu"
    },
    {
      "feedback_message": "Lorem Ipsum is simply dummy text of the printing and typesetting industry. Lorem Ipsum has been the industry's standard dummy text ever since the 1500s.",
      "feedback_raring": 3,
      "feedback_by": "Bala",
      "feedback_time": "19-01-2016 18:00:00",
      "feedback_by_url": "Bala"
    }
  ],
  "provider_profile_url": " http://cdn.shephertz.com/repository/files/458f7884154a3afc67bd5c5f24df3d1e6c0852e01e4e272ea3ed79a8d8ac6439/4adf797dc7cc07bc2f45282748d44d0ca6669219/provider_image.jpeg",
  "activities": [
    {
      "service_id": 14700,
      "activity_message": "Testing ",
      "status": "upcoming",
      "videos": [],
      "customer_email": "balamscint@gmail.com",
      "activity_name": "Grocery Service",
      "dependent_image_url": "http://cdn.shephertz.com/repository/files/458f7884154a3afc67bd5c5f24df3d1e6c0852e01e4e272ea3ed79a8d8ac6439/6ab454893564502587769da6bd9d927c38054a13/komu.jpeg",
      "activity_description": "Buy and Delivery of Required Grocery items",
      "activity_date": "2016-03-13T20:03:07.801Z",
      "dependent_name": "komu",
      "features_done":[],
      "features": [
        "potato",
        "corn"
      ],
      "images": [],
      "activity_done_date": "2016-03-13T20:03:07.801Z"
    }
  ],
  "provider_address": "Pune,Kothrud,poud 1 road",
  "provider_name": "Rushi"
}